timedeltafmt/__init__.py
timedeltafmt/py.typed
timedeltafmt-0.1.1.dist-info/LICENSE
timedeltafmt-0.1.1.dist-info/METADATA
timedeltafmt-0.1.1.dist-info/WHEEL
timedeltafmt-0.1.1.dist-info/top_level.txt
timedeltafmt-0.1.1.dist-info/RECORD
