Metadata-Version: 2.1
Name: timedeltafmt
Version: 0.1.1
Summary: Parse and format timedelta
Home-page: https://github.com/tsangwpx/timedeltafmt
Author: Aaron Tsang
License: UNKNOWN
Platform: UNKNOWN
Classifier: Programming Language :: Python :: 3
Classifier: Programming Language :: Python :: 3.7
Classifier: License :: OSI Approved :: MIT License
Classifier: Operating System :: OS Independent
Classifier: Development Status :: 4 - Beta
Classifier: Topic :: Text Processing
